pomodoroapp/__init__.py
pomodoroapp/app.py
pomodoroapp/cdapp.py
pomodoroapp/countdown.py
pomodoroapp/pomapp.py
pomodoroapp/pomodoro.py
pomodoroapp/stopwatch.py
pomodoroapp/utilityfunctions.py
tests/__init__.py
tests/test_countdown.py
tests/test_pomodoro.py
tests/test_stopwatch.py
tests/test_utilityfunctions.py
pomodoroapp-0.0.4.dist-info/LICENSE
pomodoroapp-0.0.4.dist-info/METADATA
pomodoroapp-0.0.4.dist-info/WHEEL
pomodoroapp-0.0.4.dist-info/entry_points.txt
pomodoroapp-0.0.4.dist-info/top_level.txt
pomodoroapp-0.0.4.dist-info/RECORD
