Metadata-Version: 2.1
Name: pomodoroapp
Version: 0.0.4
Summary: Pomodoro GUI App
Home-page: https://github.com/andrayantelo/pomodoroapp
Author: Andrea Anaya
Author-email: andrayantelo@gmail.com
License: UNKNOWN
Platform: UNKNOWN
Classifier: License :: OSI Approved :: GNU General Public License v3 (GPLv3)
Requires-Python: >=3.5
Requires-Dist: pygame
